.gitignore
CHANGES.rst
README.rst
setup.cfg
setup.py
tox.ini
docs/Makefile
docs/conf.py
docs/index.rst
docs/.static/logo_hi.gif
docs/.static/repoze.css
repoze/__init__.py
repoze.postoffice.egg-info/PKG-INFO
repoze.postoffice.egg-info/SOURCES.txt
repoze.postoffice.egg-info/dependency_links.txt
repoze.postoffice.egg-info/entry_points.txt
repoze.postoffice.egg-info/namespace_packages.txt
repoze.postoffice.egg-info/not-zip-safe
repoze.postoffice.egg-info/requires.txt
repoze.postoffice.egg-info/top_level.txt
repoze/postoffice/__init__.py
repoze/postoffice/api.py
repoze/postoffice/filters.py
repoze/postoffice/message.py
repoze/postoffice/queue.py
repoze/postoffice/script.py
repoze/postoffice/tests/__init__.py
repoze/postoffice/tests/borked_encoding.email
repoze/postoffice/tests/test_api.py
repoze/postoffice/tests/test_body_regexps.txt
repoze/postoffice/tests/test_filters.py
repoze/postoffice/tests/test_header_regexps.txt
repoze/postoffice/tests/test_message.py
repoze/postoffice/tests/test_queue.py