Metadata-Version: 1.0
Name: repoze.postoffice
Version: 0.23
Summary: Provides central depot for incoming mail for use by applications.
Home-page: http://www.repoze.org
Author: Chris Rossi
Author-email: repoze-dev@lists.repoze.org
License: BSD-derived (http://www.repoze.org/LICENSE.txt)
Keywords: e-mail zope repoze
Platform: UNKNOWN
Classifier: Development Status :: 4 - Beta
Classifier: Intended Audience :: Developers
Classifier: Programming Language :: Python
